turboconfig
